paulius_l_biudzetas/__init__.py
paulius_l_biudzetas/main.py
paulius_l_biudzetas/module/__init__.py
paulius_l_biudzetas/module/biudzetas.py
paulius_l_biudzetas/module/irasas.py
paulius_l_biudzetas/module/islaidu_irasas.py
paulius_l_biudzetas/module/pajamu_irasas.py
paulius_l_biudzetas/test_roberto.py
paulius_l_biudzetas-0.1.1.dist-info/METADATA
paulius_l_biudzetas-0.1.1.dist-info/WHEEL
paulius_l_biudzetas-0.1.1.dist-info/RECORD
